tests/__init__.py
tests/dont_test_markup.py
tests/test_markup.py
tests/test_palette.py
zenith/__about__.py
zenith/__init__.py
zenith/__main__.py
zenith/exceptions.py
zenith/macros.py
zenith/markup.py
zenith/palette.py
zenith/py.typed
sh40_zenith-0.10.0.dist-info/METADATA
sh40_zenith-0.10.0.dist-info/WHEEL
sh40_zenith-0.10.0.dist-info/entry_points.txt
sh40_zenith-0.10.0.dist-info/licenses/LICENSE.txt
sh40_zenith-0.10.0.dist-info/RECORD
