Metadata-Version: 2.4
Name: sh40-zenith
Version: 0.10.0
Summary: A markup language and color palette generators targeting the terminal.
Project-URL: Documentation, https://github.com/shade40/zenith#readme
Project-URL: Issues, https://github.com/shade40/zenith#issues
Project-URL: Source, https://github.com/shade40/zenith
Author-email: bczsalba <bczsalba@gmail.com>
License-Expression: MIT
License-File: LICENSE.txt
Classifier: Development Status :: 4 - Beta
Classifier: Programming Language :: Python
Classifier: Programming Language :: Python :: 3.8
Classifier: Programming Language :: Python :: 3.9
Classifier: Programming Language :: Python :: 3.10
Classifier: Programming Language :: Python :: 3.11
Classifier: Programming Language :: Python :: Implementation :: CPython
Classifier: Programming Language :: Python :: Implementation :: PyPy
Requires-Python: >=3.8
Requires-Dist: sh40-slate
